{
  "fixtures": [
    {
      "match": {
        "endpoint": "fal",
        "userMessage": "Camera holds a locked eye-level framing on the white vanity then slowly pushes in. Scarlett's hand reaches forward to lift the matte white box lid open, then fingertips press firmly into the coral lipstick bullet as direct window light catches its surface. Her delivery stays soft and reflective with minimal head movement and precise hand gestures. Bright natural light shifts slightly across the lid edge while faint dust motes drift in the beam.\n\n[SCARLETT, soft reflective]: \"One shade. One summer.\"\n\nAmbient sounds: quiet studio room tone with faint window hum. lid sliding open, fingertip press on lipstick.",
        "model": "fal-ai/kling-video/v3/pro/image-to-video",
        "turnIndex": 0,
        "hasToolResult": false
      },
      "response": {
        "json": {
          "video": {
            "url": "https://v3b.fal.media/files/b/0a9c7f4f/Hd04fOv3wskUMzO3L-VaO_output.mp4",
            "content_type": "video/mp4",
            "file_name": "output.mp4",
            "file_size": 12297609
          }
        },
        "status": 200
      }
    }
  ]
}
