{
  "request": {
    "targetHost": "queue.fal.run",
    "method": "POST",
    "pathname": "/fal-ai/flux-2/turbo",
    "bodyHash": "9cac7c6123bf5ad4"
  },
  "responses": [
    {
      "status": 200,
      "headers": {
        "access-control-allow-credentials": "true",
        "connection": "keep-alive",
        "content-length": "424",
        "content-type": "application/json",
        "date": "Fri, 08 May 2026 05:51:10 GMT",
        "strict-transport-security": "max-age=31536000; includeSubDomains",
        "vary": "origin, access-control-request-method, access-control-request-headers",
        "x-fal-request-id": "019e0623-cddb-74b3-bba5-dea98fbac6fe",
        "x-robots-tag": "noindex"
      },
      "body": {
        "status": "IN_QUEUE",
        "request_id": "019e0623-cddb-74b3-bba5-dea98fbac6fe",
        "response_url": "https://queue.fal.run/fal-ai/flux-2/requests/019e0623-cddb-74b3-bba5-dea98fbac6fe",
        "status_url": "https://queue.fal.run/fal-ai/flux-2/requests/019e0623-cddb-74b3-bba5-dea98fbac6fe/status",
        "cancel_url": "https://queue.fal.run/fal-ai/flux-2/requests/019e0623-cddb-74b3-bba5-dea98fbac6fe/cancel",
        "logs": null,
        "metrics": {},
        "queue_position": 0
      }
    }
  ]
}
